lingxingapi/__init__.py
lingxingapi/api.py
lingxingapi/errors.py
lingxingapi/fields.py
lingxingapi/utils.py
lingxingapi/ads/__init__.py
lingxingapi/ads/api.py
lingxingapi/ads/param.py
lingxingapi/ads/route.py
lingxingapi/ads/schema.py
lingxingapi/base/__init__.py
lingxingapi/base/api.py
lingxingapi/base/param.py
lingxingapi/base/route.py
lingxingapi/base/schema.py
lingxingapi/basic/__init__.py
lingxingapi/basic/api.py
lingxingapi/basic/param.py
lingxingapi/basic/route.py
lingxingapi/basic/schema.py
lingxingapi/fba/__init__.py
lingxingapi/fba/api.py
lingxingapi/fba/param.py
lingxingapi/fba/route.py
lingxingapi/fba/schema.py
lingxingapi/finance/__init__.py
lingxingapi/finance/api.py
lingxingapi/finance/param.py
lingxingapi/finance/route.py
lingxingapi/finance/schema.py
lingxingapi/product/__init__.py
lingxingapi/product/api.py
lingxingapi/product/param.py
lingxingapi/product/route.py
lingxingapi/product/schema.py
lingxingapi/purchase/__init__.py
lingxingapi/purchase/api.py
lingxingapi/purchase/param.py
lingxingapi/purchase/route.py
lingxingapi/purchase/schema.py
lingxingapi/sales/__init__.py
lingxingapi/sales/api.py
lingxingapi/sales/param.py
lingxingapi/sales/route.py
lingxingapi/sales/schema.py
lingxingapi/source/__init__.py
lingxingapi/source/api.py
lingxingapi/source/param.py
lingxingapi/source/route.py
lingxingapi/source/schema.py
lingxingapi/tools/__init__.py
lingxingapi/tools/api.py
lingxingapi/tools/param.py
lingxingapi/tools/route.py
lingxingapi/tools/schema.py
lingxingapi/warehourse/__init__.py
lingxingapi/warehourse/api.py
lingxingapi/warehourse/param.py
lingxingapi/warehourse/route.py
lingxingapi/warehourse/schema.py
lingxingapi-1.6.1.dist-info/licenses/LICENSE
lingxingapi-1.6.1.dist-info/METADATA
lingxingapi-1.6.1.dist-info/WHEEL
lingxingapi-1.6.1.dist-info/top_level.txt
lingxingapi-1.6.1.dist-info/RECORD
