Metadata-Version: 2.4
Name: lingxingapi
Version: 1.6.1
Summary: An async API client for LingXing (领星) ERP
Home-page: https://github.com/AresJef/LingXingApi
Author: Jiefu Chen
Author-email: keppa1991@163.com
License: MIT license
Keywords: async,api,lingxing,erp
Classifier: Programming Language :: Python :: 3
Classifier: Operating System :: Unix
Classifier: Operating System :: MacOS :: MacOS X
Classifier: Operating System :: Microsoft :: Windows
Requires-Python: >=3.10
License-File: LICENSE
Requires-Dist: aiohttp>=3.8.4
Requires-Dist: cytimes>=3.0.1
Requires-Dist: numpy>=1.25.2
Requires-Dist: orjson>=3.10.2
Requires-Dist: pycryptodome>=3.23.0
Requires-Dist: pydantic>=2.7.4
Requires-Dist: typing-extensions>=4.9.0
Dynamic: license-file
